{
  "kind": "collectionType",
  "collectionName": "categories",
  "info": {
    "singularName": "category",
    "pluralName": "categories",
    "displayName": "Kategorija",
    "description": ""
  },
  "options": {
    "draftAndPublish": true
  },
  "pluginOptions": {},
  "attributes": {
    "title": {
      "type": "string"
    },
    "deutsch": {
      "type": "string"
    },
    "image": {
      "allowedTypes": [
        "images"
      ],
      "type": "media",
      "multiple": false
    }
  }
}
